odoo8_addon_mrp_hook-8.0.1.0.0.99.dev14-py2.7-nspkg.pth
odoo8_addon_mrp_hook-8.0.1.0.0.99.dev14.dist-info/DESCRIPTION.rst
odoo8_addon_mrp_hook-8.0.1.0.0.99.dev14.dist-info/METADATA
odoo8_addon_mrp_hook-8.0.1.0.0.99.dev14.dist-info/RECORD
odoo8_addon_mrp_hook-8.0.1.0.0.99.dev14.dist-info/WHEEL
odoo8_addon_mrp_hook-8.0.1.0.0.99.dev14.dist-info/metadata.json
odoo8_addon_mrp_hook-8.0.1.0.0.99.dev14.dist-info/namespace_packages.txt
odoo8_addon_mrp_hook-8.0.1.0.0.99.dev14.dist-info/top_level.txt
odoo_addons/mrp_hook/README.rst
odoo_addons/mrp_hook/__init__.py
odoo_addons/mrp_hook/__openerp__.py
odoo_addons/mrp_hook/i18n/cs.po
odoo_addons/mrp_hook/i18n/de.po
odoo_addons/mrp_hook/i18n/en_US.po
odoo_addons/mrp_hook/i18n/es.po
odoo_addons/mrp_hook/i18n/fr.po
odoo_addons/mrp_hook/i18n/gl.po
odoo_addons/mrp_hook/i18n/hr.po
odoo_addons/mrp_hook/i18n/it.po
odoo_addons/mrp_hook/i18n/mrp_hook.pot
odoo_addons/mrp_hook/i18n/pt_BR.po
odoo_addons/mrp_hook/i18n/ro.po
odoo_addons/mrp_hook/i18n/sl.po
odoo_addons/mrp_hook/i18n/tr.po
odoo_addons/mrp_hook/i18n/vi_VN.po
odoo_addons/mrp_hook/i18n/zh_CN.po
odoo_addons/mrp_hook/images/image.png
odoo_addons/mrp_hook/images/image.svg
odoo_addons/mrp_hook/models/__init__.py
odoo_addons/mrp_hook/models/mrp_bom.py
odoo_addons/mrp_hook/static/description/icon.png
odoo_addons/mrp_hook/static/description/icon.svg
odoo_addons/mrp_hook/tests/__init__.py
odoo_addons/mrp_hook/tests/test_mrp_hook.py
